MANIFEST.in
rust_ext.py
setup.py
nahpackpy/__init__.py
nahpackpy/compat.py
nahpackpy/decode.py
nahpackpy/encode.py
nahpackpy/error.py
nahpackpy/ffi.py
nahpackpy/nahpack.h
nahpackpy.egg-info/PKG-INFO
nahpackpy.egg-info/SOURCES.txt
nahpackpy.egg-info/dependency_links.txt
nahpackpy.egg-info/not-zip-safe
nahpackpy.egg-info/requires.txt
nahpackpy.egg-info/top_level.txt
nahpackpy/nahpack/Cargo.toml
nahpackpy/nahpack/src/error.rs
nahpackpy/nahpack/src/ffi.rs
nahpackpy/nahpack/src/lib.rs
nahpackpy/nahpack/src/context/dynamics.rs
nahpackpy/nahpack/src/context/encodable.rs
nahpackpy/nahpack/src/context/hpack.rs
nahpackpy/nahpack/src/context/mod.rs
nahpackpy/nahpack/src/context/statics.rs
nahpackpy/nahpack/src/decode/block.rs
nahpackpy/nahpack/src/decode/huffman.rs
nahpackpy/nahpack/src/decode/integer.rs
nahpackpy/nahpack/src/decode/mod.rs
nahpackpy/nahpack/src/encode/block.rs
nahpackpy/nahpack/src/encode/huffman.rs
nahpackpy/nahpack/src/encode/integer.rs
nahpackpy/nahpack/src/encode/mod.rs