Metadata-Version: 1.1
Name: nahpackpy
Version: 0.1.0
Summary: Python HPACK library using nahpack
Home-page: https://github.com/ijl/nahpackpy
Author: ijl
Author-email: ijl@mailbox.org
License: Mozilla Public License, Version 2.0
Download-URL: https://github.com/ijl/nahpackpy/archive/0.1.0.tar.gz
Keywords: hpack http2 header compression encoding rfc 7541
Platform: UNKNOWN
Classifier: Development Status :: 4 - Beta
Classifier: Intended Audience :: Developers
Classifier: License :: OSI Approved :: Mozilla Public License 2.0 (MPL 2.0)
Classifier: Operating System :: OS Independent
Classifier: Programming Language :: Python :: 2
Classifier: Programming Language :: Python :: 2.7
Classifier: Programming Language :: Python :: 3
Classifier: Programming Language :: Python :: 3.3
Classifier: Programming Language :: Python :: 3.4
Classifier: Programming Language :: Python :: Implementation :: CPython
Classifier: Programming Language :: Python :: Implementation :: PyPy
Classifier: Programming Language :: Python
Classifier: Topic :: Internet :: WWW/HTTP
Classifier: Topic :: Software Development :: Libraries :: Python Modules
